main.py
alm_mcp-1.0.5.dist-info/licenses/LICENSE
alm_mcp-1.0.5.dist-info/METADATA
alm_mcp-1.0.5.dist-info/WHEEL
alm_mcp-1.0.5.dist-info/entry_points.txt
alm_mcp-1.0.5.dist-info/top_level.txt
alm_mcp-1.0.5.dist-info/RECORD
