Metadata-Version: 2.4
Name: alm-mcp
Version: 1.0.5
Summary: Polarion ALM MCP Server
Author-email: Huiyeoun Hwang <hy74.hwang@gmail.com>
Keywords: alm,mcp,Polarion
Requires-Python: >=3.8
License-File: LICENSE
Requires-Dist: httpx>=0.28.0
Requires-Dist: mcp>=0.3.0
Provides-Extra: dev
Requires-Dist: pytest; extra == "dev"
Requires-Dist: pytest-asyncio; extra == "dev"
Provides-Extra: license-files
Dynamic: license-file
